Workbook

Sheet 00_README
B2: ХОЛДИНГ КИНО — ВАРИАНТ C «IP-LICENSING LIGHT»
B4: Цель модели
B5: Проверить структурное обоснование net margin 67% (цель деки) за счёт добавления IP-library-контура
B6: поверх базового производственного pipeline холдинга.
B8: Методика
B9: Сохранены расчётные принципы базовой модели «Холдинг Кино.xlsx»:
B10: 1) поквартальный cashflow проекта, 12 кварталов (лист 02);
B11: 2) opex 88,5 млн ₽/год как базовый костяк холдинга;
B12: 3) распределение прибыли 60/40 до окупаемости, 50/50 после;
B13: 4) источники доходов расширены категорией IP Library (лицензирование окон + территории + форматы).
B15: Реконструкция Вариантов A и B из деки Kinoholding_Investor_Deck_v4.pptx
B16: A — Портфель продакшн-хауса as-is (5 п/м + 2 сериала, структура Кино/Реклама/Фестивали/Обучение).
... B41: Источник KPI деки: Kinoholding_Investor_Deck_v4.pptx, слайды 3, 5, 6.

Sheet 01_Вводные_C
B2: ВВОДНЫЕ ВАРИАНТА C — 3 сценария
A4: # | B4: Параметр | C4: Conservative | D4: Base | E4: Optimistic | F4: Ед. | G4: Комментарий
A5: 1 | B5: Base production revenue 2028 | C5: 1500 | D5: 632 | E5: 400 | F5: млн ₽ | G5: Cons=медленный IP-ramp; Base=backsolve под EBITDA 3000+margin 67%; Opt=IP-максимум
A6: 2 | B6: Маржа licensing | C6: 0.9 | D6: 0.95 | E6: 0.97 | F6: % | G6: Cебестоимость прав уже списана в базовом производстве; Opt — портфель AVOD/FAST
A7: 3 | B7: IP library revenue 2028 | C7: 2000 | D7: 2934 | E7: 3500 | F7: млн ₽ | G7: Base: backsolve из якорей деки (EBITDA 3000, margin 67%)
A8: 4 | B8: Доп. capex на IP-инфраструктуру | C8: 30 | D8: 40 | E8: 50 | F8: млн ₽ | G8: DAM, юр. контур, каталог, sales-инструменты
A9: 5 | B9: Доп. opex IP library / год | C9: 10 | D9: 15 | E9: 25 | F9: млн ₽ | G9: Rights mgr + sales + legal + международный контур
A10: 6 | B10: Base production revenue 2027 | C10: 698 | D10: 294 | E10: 186 | F10: млн ₽ | G10: Ramp-back от D5 по CAGR 115% (D5/2.15)
A11: 7 | B11: Base production revenue 2026 | C11: 324 | D11: 137 | E11: 86 | F11: млн ₽ | G11: Ramp-back от D10 по CAGR 115%
A12: 8 | B12: IP library revenue 2027 | C12: 570 | D12: 836 | E12: 998 | F12: млн ₽ | G12: ~28.5% от D7 (ramp-up IP-контура)
A13: 9 | B13: IP library revenue 2026 | C13: 200 | D13: 418 | E13: 500 | F13: млн ₽ | G13: MVP-библиотека с Q1 2026
A14: 10 | B14: Ставка налога на прибыль | C14: 0.2 | D14: 0.2 | E14: 0.2 | F14: % | G14: Стандартная ставка налога на прибыль РФ
A15: 11 | B15: Total revenue 2028 holding (= D5+D7) | C15: 3500 | D15: 3566 | E15: 3900 | F15: млн ₽ | G15: Derived: base production + IP library (additive)
A16: 12 | B16: Базовый opex холдинга / год | C16: 88.5 | D16: 88.5 | E16: 88.5 | F16: млн ₽ | G16: Из листа 'Расходы' базовой финмодели
... A18: 14 | B18: CAGR выручки 2025→2028 (дека) | C18: 1.15 | D18: 1.15 | E18: 1.15 | F18: % | G18: Якорь слайд 3 деки Kinoholding_Investor_Deck_v4
B20: Base-сценарий используется как активный для листов 02–05. Conservative/Optimistic — для чувствительности.

Sheet 02_Проект_flagship
B2: ПРОЕКТНЫЙ УРОВЕНЬ: flagship + IP library слой (12 кварталов, млн ₽)
B3: Базис: модель из 'Холдинг Кино.xlsx' лист PnL + дополнительный IP library-слой (ramp-up с Q5)
B5: Статья | C5: Q1 | D5: Q2 | E5: Q3 | F5: Q4 | G5: Q5 | H5: Q6 | I5: Q7 | J5: Q8 | K5: Q9 | L5: Q10 | M5: Q11 | N5: Q12 | O5: Итого
B6: БАЗОВЫЙ ПРОЕКТ
B7: Capex (производство) | C7: -312.5 | D7: -312.5 | E7: -312.5 | F7: -312.5 | G7: 0 | H7: 0 | I7: 0 | J7: 0 | K7: 0 | L7: 0 | M7: 0 | N7: 0 | O7: =SUM(C7:N7)
B8: Opex (ежеквартально) | C8: =-'01_Вводные_C'!$D$16/4 | D8: =-'01_Вводные_C'!$D$16/4 | E8: =-'01_Вводные_C'!$D$16/4 | F8: =-'01_Вводные_C'!$D$16/4 | G8: =-'01_Вводные_C'!$D$16/4 | H8: =-'01_Вводные_C'!$D$16/4 | I8: =-'01_Вводные_C'!$D$16/4 | J8: =-'01_Вводные_C'!$D$16/4 | ... N8: =-'01_Вводные_C'!$D$16/4 | O8: =SUM(C8:N8)
B9: Выручка базовая (flagship) | C9: 0 | D9: 0 | E9: 0 | F9: 0 | G9: 356.75 | H9: 356.75 | I9: 356.75 | J9: 356.75 | K9: 522.13 | L9: 522.13 | M9: 522.13 | N9: 522.13 | O9: =SUM(C9:N9)
B10: Чистый поток baseline | C10: =C7+C8+C9 | D10: =D7+D8+D9 | E10: =E7+E8+E9 | F10: =F7+F8+F9 | G10: =G7+G8+G9 | H10: =H7+H8+H9 | I10: =I7+I8+I9 | J10: =J7+J8+J9 | ... N10: =N7+N8+N9 | O10: =SUM(C10:N10)
B11: Кумулятив baseline | C11: =C10 | D11: =C11+D10 | E11: =D11+E10 | F11: =E11+F10 | G11: =F11+G10 | H11: =G11+H10 | I11: =H11+I10 | J11: =I11+J10 | K11: =J11+K10 | ... N11: =M11+N10
B13: СЛОЙ IP LIBRARY (Base-сценарий)
B14: Capex IP-инфраструктуры | C14: =-'01_Вводные_C'!D8 | D14: 0 | E14: 0 | F14: 0 | G14: 0 | H14: 0 | I14: 0 | J14: 0 | K14: 0 | L14: 0 | M14: 0 | N14: 0 | O14: =SUM(C14:N14)
B15: Opex IP library (кв.) | C15: =-'01_Вводные_C'!D9/4 | D15: =-'01_Вводные_C'!D9/4 | E15: =-'01_Вводные_C'!D9/4 | F15: =-'01_Вводные_C'!D9/4 | G15: =-'01_Вводные_C'!D9/4 | H15: =-'01_Вводные_C'!D9/4 | I15: =-'01_Вводные_C'!D9/4 | J15: =-'01_Вводные_C'!D9/4 | K15: =-'01_Вводные_C'!D9/4 | L15: =-'01_Вводные_C'!D9/4 | M15: =-'01_Вводные_C'!D9/4 | N15: =-'01_Вводные_C'!D9/4 | O15: =SUM(C15:N15)
B16: Выручка IP library (ramp) | C16: 0 | D16: 0 | E16: 0 | F16: 0 | G16: 15 | H16: 15 | I16: 15 | J16: 15 | K16: 35 | L16: 35 | M16: 35 | N16: 35 | O16: =SUM(C16:N16)
B17: Contribution IP library | C17: =C16*'01_Вводные_C'!$D$6+C14+C15 | D17: =D16*'01_Вводные_C'!$D$6+D14+D15 | E17: =E16*'01_Вводные_C'!$D$6+E14+E15 | F17: =F16*'01_Вводные_C'!$D$6+F14+F15 | G17: =G16*'01_Вводные_C'!$D$6+G14+G15 | H17: =H16*'01_Вводные_C'!$D$6+H14+H15 | I17: =I16*'01_Вводные_C'!$D$6+I14+I15 | J17: =J16*'01_Вводные_C'!$D$6+J14+J15 | ... N17: =N16*'01_Вводные_C'!$D$6+N14+N15 | O17: =SUM(C17:N17)
B19: КОМБИНИРОВАННЫЙ ПОТОК (baseline + IP library)
B20: Чистый поток Variant C | C20: =C10+C17 | D20: =D10+D17 | E20: =E10+E17 | F20: =F10+F17 | G20: =G10+G17 | H20: =H10+H17 | I20: =I10+I17 | J20: =J10+J17 | ... N20: =N10+N17 | O20: =SUM(C20:N20)
B21: Кумулятив Variant C | C21: =C20 | D21: =C21+D20 | E21: =D21+E20 | F21: =E21+F20 | G21: =F21+G20 | H21: =G21+H20 | I21: =H21+I20 | J21: =I21+J20 | K21: =J21+K20 | ... N21: =M21+N20
B22: Δ Variant C vs baseline | C22: =C20-C10 | D22: =D20-D10 | E22: =E20-E10 | F22: =F20-F10 | G22: =G20-G10 | H22: =H20-H10 | I22: =I20-I10 | J22: =J20-J10 | ... N22: =N20-N10 | O22: =SUM(C22:N22)
B24: ИТОГОВЫЕ МЕТРИКИ ПРОЕКТА
B25: Суммарный capex | C25: =SUM(C7:N7)+SUM(C14:N14)
B26: Суммарные opex (3 года) | C26: =SUM(C8:N8)+SUM(C15:N15)
B27: Суммарная выручка baseline | C27: =SUM(C9:N9)
B28: Суммарная выручка IP library | C28: =SUM(C16:N16)
B29: Суммарная выручка Variant C | C29: =C27+C28
B30: Чистый результат Variant C | C30: =O20
B31: Чистый результат baseline | C31: =O10
B32: Δ за счёт IP library | C32: =C30-C31

Sheet 03_Консолидация
B2: КОНСОЛИДАЦИЯ ХОЛДИНГА 2026–2028 — Variant C Base (млн ₽)
B4: Статья | C4: 2026 | D4: 2027 | E4: 2028 | G4: CAGR 26→28
B5: ВЫРУЧКА ПО НАПРАВЛЕНИЯМ
B6: Кино | C6: ='01_Вводные_C'!$D$11*0.4 | D6: ='01_Вводные_C'!$D$10*0.4 | E6: ='01_Вводные_C'!$D$5*0.4 | G6: =(E6/C6)^(1/2)-1
B7: Реклама | C7: ='01_Вводные_C'!$D$11*0.3 | D7: ='01_Вводные_C'!$D$10*0.3 | E7: ='01_Вводные_C'!$D$5*0.3 | G7: =(E7/C7)^(1/2)-1
B8: Фестивали | C8: ='01_Вводные_C'!$D$11*0.18 | D8: ='01_Вводные_C'!$D$10*0.18 | E8: ='01_Вводные_C'!$D$5*0.18 | G8: =(E8/C8)^(1/2)-1
B9: Обучение | C9: ='01_Вводные_C'!$D$11*0.12 | D9: ='01_Вводные_C'!$D$10*0.12 | E9: ='01_Вводные_C'!$D$5*0.12 | G9: =(E9/C9)^(1/2)-1
B10: Итого базовое производство | C10: =SUM(C6:C9) | D10: =SUM(D6:D9) | E10: =SUM(E6:E9) | G10: =(E10/C10)^(1/2)-1
B11: IP Library (новый контур) | C11: ='01_Вводные_C'!$D$13 | D11: ='01_Вводные_C'!$D$12 | E11: ='01_Вводные_C'!$D$7 | G11: =IF(C11=0,"n/a",(E11/C11)^(1/2)-1)
B12: ИТОГО ВЫРУЧКА ХОЛДИНГА | C12: =C10+C11 | D12: =D10+D11 | E12: =E10+E11 | G12: =(E12/C12)^(1/2)-1
B14: СЕБЕСТОИМОСТЬ И ОПЕРАЦИОННЫЕ РАСХОДЫ
B15: COGS базового производства | C15: =-C10*(1-'01_Вводные_C'!$D$17) | D15: =-D10*(1-'01_Вводные_C'!$D$17) | E15: =-E10*(1-'01_Вводные_C'!$D$17)
B16: COGS IP library | C16: =-C11*(1-'01_Вводные_C'!$D$6) | D16: =-D11*(1-'01_Вводные_C'!$D$6) | E16: =-E11*(1-'01_Вводные_C'!$D$6)
B17: Валовая прибыль | C17: =C12+C15+C16 | D17: =D12+D15+D16 | E17: =E12+E15+E16
B18: Gross margin % | C18: =C17/C12 | D18: =D17/D12 | E18: =E17/E12
B20: Базовый opex холдинга | C20: =-'01_Вводные_C'!$D$16 | D20: =-'01_Вводные_C'!$D$16 | E20: =-'01_Вводные_C'!$D$16
B21: Доп. opex IP library | C21: =-'01_Вводные_C'!$D$9 | D21: =-'01_Вводные_C'!$D$9 | E21: =-'01_Вводные_C'!$D$9
B22: EBITDA | C22: =C17+C20+C21 | D22: =D17+D20+D21 | E22: =E17+E20+E21
B23: EBITDA margin % | C23: =C22/C12 | D23: =D22/D12 | E23: =E22/E12
B25: Амортизация (IP capex 3 года) | C25: =-'01_Вводные_C'!$D$8/3 | D25: =-'01_Вводные_C'!$D$8/3 | E25: =-'01_Вводные_C'!$D$8/3
B26: Прибыль до налога | C26: =C22+C25 | D26: =D22+D25 | E26: =E22+E25
B27: Налог на прибыль | C27: =-MAX(C26,0)*'01_Вводные_C'!$D$14 | D27: =-MAX(D26,0)*'01_Вводные_C'!$D$14 | E27: =-MAX(E26,0)*'01_Вводные_C'!$D$14
B28: ЧИСТАЯ ПРИБЫЛЬ | C28: =C26+C27 | D28: =D26+D27 | E28: =E26+E27
B29: NET MARGIN % (Variant C) | C29: =C28/C12 | D29: =D28/D12 | E29: =E28/E12
B31: КУМУЛЯТИВНЫЕ ПОКАЗАТЕЛИ 2026–2028
B32: Кумулятивная выручка | C32: =SUM(C12:E12)
B33: Кумулятивный EBITDA | C33: =SUM(C22:E22)
B34: Кумулятивная чистая прибыль | C34: =SUM(C28:E28)
B35: Средний EBITDA margin | C35: =SUMPRODUCT(C22:E22)/SUMPRODUCT(C12:E12)
B36: Средний Net margin | C36: =SUMPRODUCT(C28:E28)/SUMPRODUCT(C12:E12)

Sheet 04_Сверка_с_декой
B2: СВЕРКА С KPI ДЕКИ Kinoholding_Investor_Deck_v4
B4: KPI деки (слайды 3, 5, 6) | C4: Дека (заявлено) | D4: Модель (Variant C) | E4: Δ | F4: Комментарий / эпистемический статус
B5: EBITDA 2028, млн ₽ ⚓ ЯКОРЬ | C5: 3000 | D5: ='03_Консолидация'!E22 | E5: =D5-C5 | F5: ЯКОРЬ деки. Base-сценарий построен backsolve-методом под эту цифру.
B6: Net margin 2028 ⚓ ЯКОРЬ | C6: 0.67 | D6: ='03_Консолидация'!E29 | E6: =D6-C6 | F6: ЯКОРЬ деки. Достигается в Base через IP library как аддитивный слой.
B7: Чистая прибыль 2028, млн ₽ | C7: 2389 | D7: ='03_Консолидация'!E28 | E7: =D7-C7 | F7: Backsolve: 0.67 × 3566 = 2389. Дека округляет до 2 млрд.
B8: CAGR базового производства 2026→2028 | C8: 1.15 | D8: ='03_Консолидация'!G10 | E8: =D8-C8 | F8: Якорь слайд 3 деки 115% применим к базовому производству (137→294→632 = 115% CAGR). Total выручка растёт быстрее, т.к. IP library стартует с MVP-базы.
B9: Выручка 2028, млн ₽ (справочно) | C9: 3000 | D9: ='03_Консолидация'!E12 | E9: =D9-C9 | F9: НЕ якорь. Дека заявляет 3000, модель даёт 3566 (632 базовое + 2934 IP library). Δ+566 — упущенный upside.
B10: Базовое производство 2028, млн ₽ | C10: 3000 | D10: ='03_Консолидация'!E10 | E10: =D10-C10 | F10: Backsolve даёт 632 млн — намного ниже деки. Без IP library деке пришлось бы закладывать 3000 с невозможной маржой.
B11: IP library 2028, млн ₽ | C11: 0 | D11: ='03_Консолидация'!E11 | E11: =D11-C11 | F11: Новый контур (в деке отсутствует как строка). Base: 2934 млн ≈ 82% выручки.
B12: EBITDA кумул. 2026–2028, млн ₽ (справ.) | C12: — | D12: =SUM('03_Консолидация'!C22:E22) | E12: — | F12: В деке не заявлено; справочно. Сумма 3 лет: 362+838+3000 ≈ 4200 млн (2026/2027 в ramp-up).
B13: Breakeven (проект, кумулятив>0) | C13: Q4 2026 | D13: =IF('02_Проект_flagship'!K11>0,"Q4 2026","позже Q8 2027") | E13: — | F13: Дека заявляет Q4 2026. Модель проекта показывает кумулятивный выход в плюс позже — см. строку «Кумулятив Variant C».
B15: НАХОДКИ ВЕРИФИКАЦИИ (П5 МАКСИМУМ)
B16: F1. ЯКОРЯ деки (EBITDA 2028 = 3 млрд, Net margin 67%) достижимы структурно только при доле IP library ~82% в total revenue 2028. Base-сценарий построен обратным счётом (backsolve): base_rev 632 + ip_rev 2934 = 3566; gross 3103.5; EBITDA 3000; net 2389; margin 67.00%.
B17: F2. Выручка 2028 = 3 000 млн из деки — НЕ якорь. При фиксированных анкерах EBITDA/margin backsolve даёт total revenue 3566 млн (выше деки на 566 млн), из которых базовое производство сжимается до 632 млн, а IP library становится основным драйвером с 2934 млн.
B18: F3. Без IP library деке пришлось бы закладывать 3000 млн выручки от базового производства при gross margin >80% — это невозможно для реального продакшн-хауса (прокат+реклама+фестивали+обучение дают смешанную маржу ~50%). IP library — ЕДИНСТВЕННЫЙ операционно реалистичный путь к 67%.
B19: F4. Чистая прибыль 2389 млн ₽ = 67% × 3566 = backsolve-согласована. Дека округляет до 2 млрд — совместимо в пределах 20% допуска точности инвестиционных deck-цифр.
B20: F5. CAGR 115% от базы 2025 ~300 млн даёт стандартную траекторию 300 → 645 → 1390 → 3000 млн (по базовой производственной линии). IP library добавляется сверху и к 2028 превышает базовое производство кратно — это и есть структурное превращение холдинга из продакшн-хауса в медиа-компанию.
B21: F6. Стыковка с Q2 2027 international deal (слайд 6 деки): в сценариях без IP library эта сделка операционно беспочвенна — нечего лицензировать. В Variant C Base к Q2 2027 IP library генерирует 836 млн/год — есть реальный каталог прав, международная сделка обретает смысл.
B22: F7. Скрытое допущение Base: IP library формируется ИЗ тайтлов, созданных базовым pipeline (cost of rights уже списан в базовом производстве). Licensing gross margin 95% = чистая renta от уже существующего актива. Это корректно только если IP-контур запущен в 2026 и права законтрактованы грамотно — критический юридический риск.
B23: F8. Cons-сценарий (IP library 2000 млн, margin 90%) даёт net margin ~56% — якоря НЕ достигаются. Это реалистичный downside при медленном ramp-up international rights market. Opt-сценарий (IP 3500 млн, margin 97%) даёт net margin ~71% — upside при агрессивном AVOD/FAST rollout.
B24: F9. Единица капитализации меняется: Variant C = медиа-компания (EV/EBITDA ~9×) против продакшн-хауса A/B (~5–6×). При одинаковой EBITDA 3 млрд implied valuation Variant C ~27 млрд против ~18 млрд у A/B — Δ +9 млрд структурно обусловлена IP-библиотекой.

Sheet 05_Сравнение_A_B_C
B2: СРАВНЕНИЕ ВАРИАНТОВ A / B / C (2028, Base)
B4: Метрика | C4: Variant A (дека as-is) | D4: Variant B (производств. максимум) | E4: Variant C (IP-library light)
B6: Pipeline 2028 | C6: 5 п/м + 2 сериала (as-is) | D6: 7–8 п/м + 3–4 сериала (capex-heavy) | E6: базовый pipeline + IP library (82% выручки)
B7: Capex на производство (итого), млн ₽ | C7: 1250 | D7: 1900 | E7: 1250
B8: Capex IP-инфраструктура, млн ₽ | C8: 0 | D8: 0 | E8: ='01_Вводные_C'!$D$8
B9: Opex холдинга / год, млн ₽ | C9: 88.5 | D9: 95 | E9: ='01_Вводные_C'!$D$16+'01_Вводные_C'!$D$9
B10: Выручка 2028, млн ₽ | C10: 3000 | D10: 3300 | E10: ='03_Консолидация'!E12
B11: Gross margin (blended) | C11: 0.5 | D11: 0.45 | E11: ='03_Консолидация'!E17/'03_Консолидация'!E12
B12: Валовая прибыль 2028, млн ₽ | C12: =C10*C11 | D12: =D10*D11 | E12: ='03_Консолидация'!E17
B13: EBITDA 2028, млн ₽ | C13: =C12-C9 | D13: =D12-D9 | E13: ='03_Консолидация'!E22
B14: EBITDA margin 2028 | C14: =C13/C10 | D14: =D13/D10 | E14: =E13/E10
B15: Чистая прибыль 2028, млн ₽ | C15: =C13*(1-'01_Вводные_C'!$D$14) | D15: =D13*(1-'01_Вводные_C'!$D$14) | E15: ='03_Консолидация'!E28
B16: Net margin 2028 | C16: =C15/C10 | D16: =D15/D10 | E16: =E15/E10
B17: Зависимость от единичных релизов | C17: Высокая | D17: Очень высокая | E17: Низкая (библиотека как страховка)
B18: Стыковка с Q2 2027 international deal (дека) | C18: Нет каталога — нечего лицензировать | D18: Нет (фокус на производственном объёме) | E18: ДА — к Q2 2027 IP library даёт 836 млн/год
B19: Капитализационный класс | C19: Продакшн-хаус | D19: Продакшн-хаус | E19: Медиа-компания (A24/Gaumont-like)
B20: EV/EBITDA 2028 ориентир | C20: 6 | D20: 5 | E20: 9
B21: Implied valuation 2028, млн ₽ | C21: =C13*C20 | D21: =D13*D20 | E21: =E13*E20
B23: Варианты A/B реконструированы из Kinoholding_Investor_Deck_v4 (A = дека as-is, B = производственный максимум). Variant C — активная модель (данные из листа 03_Консолидация).
B24: Formula note: EBITDA A/B = Revenue × Gross margin − Opex/год (упрощённая модель без D&A); Variant C включает полную цепочку (COGS + D&A + налог).

Sheet 06_Чувствительность
B2: ЧУВСТВИТЕЛЬНОСТЬ NET MARGIN 2028 — Доля licensing × Маржа licensing
B4: Доля licensing \ Маржа licensing | C4: 0.8 | D4: 0.85 | E4: 0.9 | F4: 0.92 | G4: 0.95 | H4: 0.97
B5: 0.4 | C5: =((('01_Вводные_C'!$D$15)*(1-$B5)*'01_Вводные_C'!$D$17 + ('01_Вводные_C'!$D$15)*$B5*C$4 - '01_Вводные_C'!$D$16 - '01_Вводные_C'!$D$9 - '01_Вводные_C'!$D$8/3)*(1-'01_Вводные_C'!$D$14))/'01_Вводные_C'!$D$15 | D5: =((('01_Вводные_C'!$D$15)*(1-$B5)*'01_Вводные_C'!$D$17 + ('01_Вводные_C'!$D$15)*$B5*D$4 - '01_Вводные_C'!$D$16 - '01_Вводные_C'!$D$9 - '01_Вводные_C'!$D$8/3)*(1-'01_Вводные_C'!$D$14))/'01_Вводные_C'!$D$15 | E5: =((('01_Вводные_C'!$D$15)*(1-$B5)*'01_Вводные_C'!$D$17 + ('01_Вводные_C'!$D$15)*$B5*E$4 - '01_Вводные_C'!$D$16 - '01_Вводные_C'!$D$9 - '01_Вводные_C'!$D$8/3)*(1-'01_Вводные_C'!$D$14))/'01_Вводные_C'!$D$15 | F5: =((('01_Вводные_C'!$D$15)*(1-$B5)*'01_Вводные_C'!$D$17 + ('01_Вводные_C'!$D$15)*$B5*F$4 - '01_Вводные_C'!$D$16 - '01_Вводные_C'!$D$9 - '01_Вводные_C'!$D$8/3)*(1-'01_Вводные_C'!$D$14))/'01_Вводные_C'!$D$15 | G5: =((('01_Вводные_C'!$D$15)*(1-$B5)*'01_Вводные_C'!$D$17 + ('01_Вводные_C'!$D$15)*$B5*G$4 - '01_Вводные_C'!$D$16 - '01_Вводные_C'!$D$9 - '01_Вводные_C'!$D$8/3)*(1-'01_Вводные_C'!$D$14))/'01_Вводные_C'!$D$15 | H5: =((('01_Вводные_C'!$D$15)*(1-$B5)*'01_Вводные_C'!$D$17 + ('01_Вводные_C'!$D$15)*$B5*H$4 - '01_Вводные_C'!$D$16 - '01_Вводные_C'!$D$9 - '01_Вводные_C'!$D$8/3)*(1-'01_Вводные_C'!$D$14))/'01_Вводные_C'!$D$15
B6: 0.5 | C6: =((('01_Вводные_C'!$D$15)*(1-$B6)*'01_Вводные_C'!$D$17 + ('01_Вводные_C'!$D$15)*$B6*C$4 - '01_Вводные_C'!$D$16 - '01_Вводные_C'!$D$9 - '01_Вводные_C'!$D$8/3)*(1-'01_Вводные_C'!$D$14))/'01_Вводные_C'!$D$15 | D6: =((('01_Вводные_C'!$D$15)*(1-$B6)*'01_Вводные_C'!$D$17 + ('01_Вводные_C'!$D$15)*$B6*D$4 - '01_Вводные_C'!$D$16 - '01_Вводные_C'!$D$9 - '01_Вводные_C'!$D$8/3)*(1-'01_Вводные_C'!$D$14))/'01_Вводные_C'!$D$15 | E6: =((('01_Вводные_C'!$D$15)*(1-$B6)*'01_Вводные_C'!$D$17 + ('01_Вводные_C'!$D$15)*$B6*E$4 - '01_Вводные_C'!$D$16 - '01_Вводные_C'!$D$9 - '01_Вводные_C'!$D$8/3)*(1-'01_Вводные_C'!$D$14))/'01_Вводные_C'!$D$15 | F6: =((('01_Вводные_C'!$D$15)*(1-$B6)*'01_Вводные_C'!$D$17 + ('01_Вводные_C'!$D$15)*$B6*F$4 - '01_Вводные_C'!$D$16 - '01_Вводные_C'!$D$9 - '01_Вводные_C'!$D$8/3)*(1-'01_Вводные_C'!$D$14))/'01_Вводные_C'!$D$15 | G6: =((('01_Вводные_C'!$D$15)*(1-$B6)*'01_Вводные_C'!$D$17 + ('01_Вводные_C'!$D$15)*$B6*G$4 - '01_Вводные_C'!$D$16 - '01_Вводные_C'!$D$9 - '01_Вводные_C'!$D$8/3)*(1-'01_Вводные_C'!$D$14))/'01_Вводные_C'!$D$15 | H6: =((('01_Вводные_C'!$D$15)*(1-$B6)*'01_Вводные_C'!$D$17 + ('01_Вводные_C'!$D$15)*$B6*H$4 - '01_Вводные_C'!$D$16 - '01_Вводные_C'!$D$9 - '01_Вводные_C'!$D$8/3)*(1-'01_Вводные_C'!$D$14))/'01_Вводные_C'!$D$15
B7: 0.6 | C7: =((('01_Вводные_C'!$D$15)*(1-$B7)*'01_Вводные_C'!$D$17 + ('01_Вводные_C'!$D$15)*$B7*C$4 - '01_Вводные_C'!$D$16 - '01_Вводные_C'!$D$9 - '01_Вводные_C'!$D$8/3)*(1-'01_Вводные_C'!$D$14))/'01_Вводные_C'!$D$15 | D7: =((('01_Вводные_C'!$D$15)*(1-$B7)*'01_Вводные_C'!$D$17 + ('01_Вводные_C'!$D$15)*$B7*D$4 - '01_Вводные_C'!$D$16 - '01_Вводные_C'!$D$9 - '01_Вводные_C'!$D$8/3)*(1-'01_Вводные_C'!$D$14))/'01_Вводные_C'!$D$15 | E7: =((('01_Вводные_C'!$D$15)*(1-$B7)*'01_Вводные_C'!$D$17 + ('01_Вводные_C'!$D$15)*$B7*E$4 - '01_Вводные_C'!$D$16 - '01_Вводные_C'!$D$9 - '01_Вводные_C'!$D$8/3)*(1-'01_Вводные_C'!$D$14))/'01_Вводные_C'!$D$15 | F7: =((('01_Вводные_C'!$D$15)*(1-$B7)*'01_Вводные_C'!$D$17 + ('01_Вводные_C'!$D$15)*$B7*F$4 - '01_Вводные_C'!$D$16 - '01_Вводные_C'!$D$9 - '01_Вводные_C'!$D$8/3)*(1-'01_Вводные_C'!$D$14))/'01_Вводные_C'!$D$15 | G7: =((('01_Вводные_C'!$D$15)*(1-$B7)*'01_Вводные_C'!$D$17 + ('01_Вводные_C'!$D$15)*$B7*G$4 - '01_Вводные_C'!$D$16 - '01_Вводные_C'!$D$9 - '01_Вводные_C'!$D$8/3)*(1-'01_Вводные_C'!$D$14))/'01_Вводные_C'!$D$15 | H7: =((('01_Вводные_C'!$D$15)*(1-$B7)*'01_Вводные_C'!$D$17 + ('01_Вводные_C'!$D$15)*$B7*H$4 - '01_Вводные_C'!$D$16 - '01_Вводные_C'!$D$9 - '01_Вводные_C'!$D$8/3)*(1-'01_Вводные_C'!$D$14))/'01_Вводные_C'!$D$15
B8: 0.7 | C8: =((('01_Вводные_C'!$D$15)*(1-$B8)*'01_Вводные_C'!$D$17 + ('01_Вводные_C'!$D$15)*$B8*C$4 - '01_Вводные_C'!$D$16 - '01_Вводные_C'!$D$9 - '01_Вводные_C'!$D$8/3)*(1-'01_Вводные_C'!$D$14))/'01_Вводные_C'!$D$15 | D8: =((('01_Вводные_C'!$D$15)*(1-$B8)*'01_Вводные_C'!$D$17 + ('01_Вводные_C'!$D$15)*$B8*D$4 - '01_Вводные_C'!$D$16 - '01_Вводные_C'!$D$9 - '01_Вводные_C'!$D$8/3)*(1-'01_Вводные_C'!$D$14))/'01_Вводные_C'!$D$15 | E8: =((('01_Вводные_C'!$D$15)*(1-$B8)*'01_Вводные_C'!$D$17 + ('01_Вводные_C'!$D$15)*$B8*E$4 - '01_Вводные_C'!$D$16 - '01_Вводные_C'!$D$9 - '01_Вводные_C'!$D$8/3)*(1-'01_Вводные_C'!$D$14))/'01_Вводные_C'!$D$15 | F8: =((('01_Вводные_C'!$D$15)*(1-$B8)*'01_Вводные_C'!$D$17 + ('01_Вводные_C'!$D$15)*$B8*F$4 - '01_Вводные_C'!$D$16 - '01_Вводные_C'!$D$9 - '01_Вводные_C'!$D$8/3)*(1-'01_Вводные_C'!$D$14))/'01_Вводные_C'!$D$15 | G8: =((('01_Вводные_C'!$D$15)*(1-$B8)*'01_Вводные_C'!$D$17 + ('01_Вводные_C'!$D$15)*$B8*G$4 - '01_Вводные_C'!$D$16 - '01_Вводные_C'!$D$9 - '01_Вводные_C'!$D$8/3)*(1-'01_Вводные_C'!$D$14))/'01_Вводные_C'!$D$15 | H8: =((('01_Вводные_C'!$D$15)*(1-$B8)*'01_Вводные_C'!$D$17 + ('01_Вводные_C'!$D$15)*$B8*H$4 - '01_Вводные_C'!$D$16 - '01_Вводные_C'!$D$9 - '01_Вводные_C'!$D$8/3)*(1-'01_Вводные_C'!$D$14))/'01_Вводные_C'!$D$15
B9: 0.8 | C9: =((('01_Вводные_C'!$D$15)*(1-$B9)*'01_Вводные_C'!$D$17 + ('01_Вводные_C'!$D$15)*$B9*C$4 - '01_Вводные_C'!$D$16 - '01_Вводные_C'!$D$9 - '01_Вводные_C'!$D$8/3)*(1-'01_Вводные_C'!$D$14))/'01_Вводные_C'!$D$15 | D9: =((('01_Вводные_C'!$D$15)*(1-$B9)*'01_Вводные_C'!$D$17 + ('01_Вводные_C'!$D$15)*$B9*D$4 - '01_Вводные_C'!$D$16 - '01_Вводные_C'!$D$9 - '01_Вводные_C'!$D$8/3)*(1-'01_Вводные_C'!$D$14))/'01_Вводные_C'!$D$15 | E9: =((('01_Вводные_C'!$D$15)*(1-$B9)*'01_Вводные_C'!$D$17 + ('01_Вводные_C'!$D$15)*$B9*E$4 - '01_Вводные_C'!$D$16 - '01_Вводные_C'!$D$9 - '01_Вводные_C'!$D$8/3)*(1-'01_Вводные_C'!$D$14))/'01_Вводные_C'!$D$15 | F9: =((('01_Вводные_C'!$D$15)*(1-$B9)*'01_Вводные_C'!$D$17 + ('01_Вводные_C'!$D$15)*$B9*F$4 - '01_Вводные_C'!$D$16 - '01_Вводные_C'!$D$9 - '01_Вводные_C'!$D$8/3)*(1-'01_Вводные_C'!$D$14))/'01_Вводные_C'!$D$15 | G9: =((('01_Вводные_C'!$D$15)*(1-$B9)*'01_Вводные_C'!$D$17 + ('01_Вводные_C'!$D$15)*$B9*G$4 - '01_Вводные_C'!$D$16 - '01_Вводные_C'!$D$9 - '01_Вводные_C'!$D$8/3)*(1-'01_Вводные_C'!$D$14))/'01_Вводные_C'!$D$15 | H9: =((('01_Вводные_C'!$D$15)*(1-$B9)*'01_Вводные_C'!$D$17 + ('01_Вводные_C'!$D$15)*$B9*H$4 - '01_Вводные_C'!$D$16 - '01_Вводные_C'!$D$9 - '01_Вводные_C'!$D$8/3)*(1-'01_Вводные_C'!$D$14))/'01_Вводные_C'!$D$15
B10: 0.82 | C10: =((('01_Вводные_C'!$D$15)*(1-$B10)*'01_Вводные_C'!$D$17 + ('01_Вводные_C'!$D$15)*$B10*C$4 - '01_Вводные_C'!$D$16 - '01_Вводные_C'!$D$9 - '01_Вводные_C'!$D$8/3)*(1-'01_Вводные_C'!$D$14))/'01_Вводные_C'!$D$15 | D10: =((('01_Вводные_C'!$D$15)*(1-$B10)*'01_Вводные_C'!$D$17 + ('01_Вводные_C'!$D$15)*$B10*D$4 - '01_Вводные_C'!$D$16 - '01_Вводные_C'!$D$9 - '01_Вводные_C'!$D$8/3)*(1-'01_Вводные_C'!$D$14))/'01_Вводные_C'!$D$15 | E10: =((('01_Вводные_C'!$D$15)*(1-$B10)*'01_Вводные_C'!$D$17 + ('01_Вводные_C'!$D$15)*$B10*E$4 - '01_Вводные_C'!$D$16 - '01_Вводные_C'!$D$9 - '01_Вводные_C'!$D$8/3)*(1-'01_Вводные_C'!$D$14))/'01_Вводные_C'!$D$15 | F10: =((('01_Вводные_C'!$D$15)*(1-$B10)*'01_Вводные_C'!$D$17 + ('01_Вводные_C'!$D$15)*$B10*F$4 - '01_Вводные_C'!$D$16 - '01_Вводные_C'!$D$9 - '01_Вводные_C'!$D$8/3)*(1-'01_Вводные_C'!$D$14))/'01_Вводные_C'!$D$15 | G10: =((('01_Вводные_C'!$D$15)*(1-$B10)*'01_Вводные_C'!$D$17 + ('01_Вводные_C'!$D$15)*$B10*G$4 - '01_Вводные_C'!$D$16 - '01_Вводные_C'!$D$9 - '01_Вводные_C'!$D$8/3)*(1-'01_Вводные_C'!$D$14))/'01_Вводные_C'!$D$15 | H10: =((('01_Вводные_C'!$D$15)*(1-$B10)*'01_Вводные_C'!$D$17 + ('01_Вводные_C'!$D$15)*$B10*H$4 - '01_Вводные_C'!$D$16 - '01_Вводные_C'!$D$9 - '01_Вводные_C'!$D$8/3)*(1-'01_Вводные_C'!$D$14))/'01_Вводные_C'!$D$15
B11: 0.9 | C11: =((('01_Вводные_C'!$D$15)*(1-$B11)*'01_Вводные_C'!$D$17 + ('01_Вводные_C'!$D$15)*$B11*C$4 - '01_Вводные_C'!$D$16 - '01_Вводные_C'!$D$9 - '01_Вводные_C'!$D$8/3)*(1-'01_Вводные_C'!$D$14))/'01_Вводные_C'!$D$15 | D11: =((('01_Вводные_C'!$D$15)*(1-$B11)*'01_Вводные_C'!$D$17 + ('01_Вводные_C'!$D$15)*$B11*D$4 - '01_Вводные_C'!$D$16 - '01_Вводные_C'!$D$9 - '01_Вводные_C'!$D$8/3)*(1-'01_Вводные_C'!$D$14))/'01_Вводные_C'!$D$15 | E11: =((('01_Вводные_C'!$D$15)*(1-$B11)*'01_Вводные_C'!$D$17 + ('01_Вводные_C'!$D$15)*$B11*E$4 - '01_Вводные_C'!$D$16 - '01_Вводные_C'!$D$9 - '01_Вводные_C'!$D$8/3)*(1-'01_Вводные_C'!$D$14))/'01_Вводные_C'!$D$15 | F11: =((('01_Вводные_C'!$D$15)*(1-$B11)*'01_Вводные_C'!$D$17 + ('01_Вводные_C'!$D$15)*$B11*F$4 - '01_Вводные_C'!$D$16 - '01_Вводные_C'!$D$9 - '01_Вводные_C'!$D$8/3)*(1-'01_Вводные_C'!$D$14))/'01_Вводные_C'!$D$15 | G11: =((('01_Вводные_C'!$D$15)*(1-$B11)*'01_Вводные_C'!$D$17 + ('01_Вводные_C'!$D$15)*$B11*G$4 - '01_Вводные_C'!$D$16 - '01_Вводные_C'!$D$9 - '01_Вводные_C'!$D$8/3)*(1-'01_Вводные_C'!$D$14))/'01_Вводные_C'!$D$15 | H11: =((('01_Вводные_C'!$D$15)*(1-$B11)*'01_Вводные_C'!$D$17 + ('01_Вводные_C'!$D$15)*$B11*H$4 - '01_Вводные_C'!$D$16 - '01_Вводные_C'!$D$9 - '01_Вводные_C'!$D$8/3)*(1-'01_Вводные_C'!$D$14))/'01_Вводные_C'!$D$15
B13: Жёлтая заливка = ячейка Base Variant C (IP share 82% × margin 95% = 67% net margin)
B15: Целевая маржа деки: 67% (якорь). Ячейки ≥67% — комбинации, где anchor достижим.
B16: Вывод: 67% достижим только при доле IP library ≥80% и licensing gross margin ≥90%. Это жёсткое структурное условие: без IP library анкер недостижим ни при какой комбинации производственных параметров.
B17: Отсюда стратегический тезис: деку обязывает IP library. Base Variant C — не выбор, а backsolve из анкеров.

Sheet 07_Roadmap
B2: ROADMAP 2026–2028 — Вариант C stage-gate
B4: Период | C4: Milestone | D4: Связь с декой / Variant C | E4: Статус
B5: Q1 2026 | C5: Юридический контур IP library: каталогизация прав flagship-тайтлов, DAM-система | D5: Capex 40 млн ₽ — старт | E5: Критический
B6: Q2 2026 | C6: Запуск 2 п/м и 1 сериала (дека, слайд 6) | D6: Базовый pipeline — Variant A/C общий | E6: Дека
B7: Q2 2026 | C7: Найм 2 чел. в IP library: rights manager + international sales | D7: Opex +10 млн/год | E7: Variant C
B8: Q3 2026 | C8: MVP библиотеки: 1–2 тайтла с rights bundling под theatrical + SVOD эксклюзив | D8: Старт IP-монетизации | E8: Variant C
B9: Q4 2026 | C9: Breakeven EBITDA (дека, слайд 6) | D9: Проверить: модель даёт позже | E9: Дека / риск
B10: Q1 2027 | C10: 3 тайтла в библиотеке, первые domestic licensing сделки (TV, SVOD window resale) | D10: IP revenue ramp 150 млн/год | E10: Variant C
B11: Q2 2027 | C11: INTERNATIONAL LICENSING DEAL — СНГ + BRICS (дека, слайд 6) | D11: КЛЮЧЕВАЯ ВЕХА. Без IP library — нечего продавать | E11: Дека ↔ C
B12: Q3 2027 | C12: Format library: 2–3 форматных адаптации под локализации в BRICS | D12: Расширение library от own-IP к format-IP | E12: Variant C
B13: Q4 2027 | C13: Выход на 5 тайтлов в библиотеке, оформление sales-пакета под роадшоу 2028 | D13: Промежуточный чекпойнт | E13: Variant C
B14: Q1 2028 | C14: Подписание 2–3 international deals (AVOD/FAST + territorial) | D14: Ramp IP revenue к target 525 млн/год | E14: Variant C
B15: Q2 2028 | C15: Расширение библиотеки до 10+ тайтлов (включая сериалы 2-го сезона, мерч-бренды) | D15: Target объём library Base | E15: Variant C
B16: Q4 2028 | C16: EBITDA 3 млрд ₽ (дека, слайд 6). Подготовка Series B / выход | D16: Целевой KPI деки; sanity-check Variant C | E16: Дека
